django_basket/__init__.py
django_basket/admin.py
django_basket/apps.py
django_basket/session_backend.py
django_basket/settings.py
django_basket/shortcuts.py
django_basket/utils.py
django_basket/contrib/__init__.py
django_basket/contrib/base.py
django_basket/contrib/basket.py
django_basket/contrib/item.py
django_basket/contrib/merging.py
django_basket/contrib/selectors.py
django_basket/locale/__init__.py
django_basket/migrations/__init__.py
django_basket/models/__init__.py
django_basket/models/basket.py
django_basket/models/item.py
django_basket/rest/__init__.py
django_basket/rest/serializers.py
django_basket/rest/urls.py
django_basket/rest/views.py
django_basket/tests/__init__.py
django_basket/tests/utils.py
django_basket/tests/base/__init__.py
django_basket/tests/base/test_aggregators.py
django_basket/tests/base/test_api.py
django_basket/tests/base/test_contrib.py
django_basket/tests/default_rest/__init__.py
django_basket/tests/default_rest/tests.py
django_basket/tests/dynamic/__init__.py
django_basket/tests/dynamic/test_aggregators.py
django_basket/tests/migrations/0001_initial.py
django_basket/tests/migrations/0002_auto_20210316_1654.py
django_basket/tests/migrations/__init__.py
django_basket/tests/settings/__init__.py
django_basket/tests/settings/default_rest.py
django_basket/tests/settings/dynamic_settings.py
django_basket/tests/settings/settings.py
django_ib_basket-0.2.dist-info/LICENSE
django_ib_basket-0.2.dist-info/METADATA
django_ib_basket-0.2.dist-info/WHEEL
django_ib_basket-0.2.dist-info/top_level.txt
django_ib_basket-0.2.dist-info/RECORD
